streamlit_component_loader-0.7.7.dist-info/licenses/LICENSE
streamlit_plugins/components/loader/__init__.py
streamlit_component_loader-0.7.7.dist-info/METADATA
streamlit_component_loader-0.7.7.dist-info/WHEEL
streamlit_component_loader-0.7.7.dist-info/top_level.txt
streamlit_component_loader-0.7.7.dist-info/RECORD
