Metadata-Version: 2.4
Name: streamlit-component-loader
Version: 0.7.7
Summary: Components and Frameworks to give new features to streamlit
Home-page: https://github.com/quiradev/streamlit-plugins
Author: Victor Quilon Ranera
Author-email: v.quilonr@gmail.com
License: MIT
Keywords: streamlit,plugins,components,loader
Classifier: Intended Audience :: Developers
Classifier: Programming Language :: Python
Classifier: Programming Language :: Python :: 3.10
Classifier: Programming Language :: Python :: 3.11
Requires-Python: >=3.10
License-File: LICENSE
Requires-Dist: streamlit>=1.36.0
Dynamic: author
Dynamic: author-email
Dynamic: classifier
Dynamic: description-content-type
Dynamic: home-page
Dynamic: keywords
Dynamic: license
Dynamic: license-file
Dynamic: requires-dist
Dynamic: requires-python
Dynamic: summary
